Lightflow_Filesystem-1.6.0.dist-info/DESCRIPTION.rst
Lightflow_Filesystem-1.6.0.dist-info/METADATA
Lightflow_Filesystem-1.6.0.dist-info/RECORD
Lightflow_Filesystem-1.6.0.dist-info/WHEEL
Lightflow_Filesystem-1.6.0.dist-info/metadata.json
Lightflow_Filesystem-1.6.0.dist-info/top_level.txt
lightflow_filesystem/__init__.py
lightflow_filesystem/chmod_task.py
lightflow_filesystem/chown_task.py
lightflow_filesystem/copy_task.py
lightflow_filesystem/exceptions.py
lightflow_filesystem/glob_task.py
lightflow_filesystem/makedir_task.py
lightflow_filesystem/move_task.py
lightflow_filesystem/newline_trigger_task.py
lightflow_filesystem/notify_trigger_task.py
lightflow_filesystem/remove_task.py
lightflow_filesystem/walk_task.py
